tesseract_pack/__init__.py
tesseract_pack/ambiguous_words.1.html
tesseract_pack/ambiguous_words.exe
tesseract_pack/classifier_tester.1.html
tesseract_pack/classifier_tester.exe
tesseract_pack/cntraining.1.html
tesseract_pack/cntraining.exe
tesseract_pack/combine_lang_model.1.html
tesseract_pack/combine_lang_model.exe
tesseract_pack/combine_tessdata.1.html
tesseract_pack/combine_tessdata.exe
tesseract_pack/dawg2wordlist.1.html
tesseract_pack/dawg2wordlist.exe
tesseract_pack/explain.txt
tesseract_pack/iconv.dll
tesseract_pack/icudt64.dll
tesseract_pack/icuin64.dll
tesseract_pack/icuuc64.dll
tesseract_pack/libarchive-13.dll
tesseract_pack/libbz2-1.dll
tesseract_pack/libcairo-2.dll
tesseract_pack/libcurl-4.dll
tesseract_pack/libeay32.dll
tesseract_pack/libexpat-1.dll
tesseract_pack/libffi-6.dll
tesseract_pack/libfontconfig-1.dll
tesseract_pack/libfreetype-6.dll
tesseract_pack/libgcc_s_seh-1.dll
tesseract_pack/libgif-7.dll
tesseract_pack/libglib-2.0-0.dll
tesseract_pack/libgobject-2.0-0.dll
tesseract_pack/libgomp-1.dll
tesseract_pack/libharfbuzz-0.dll
tesseract_pack/libidn2-0.dll
tesseract_pack/libintl-8.dll
tesseract_pack/libjbig-2.dll
tesseract_pack/libjpeg-8.dll
tesseract_pack/liblept-5.dll
tesseract_pack/liblz4-1.dll
tesseract_pack/liblzma-5.dll
tesseract_pack/liblzo2-2.dll
tesseract_pack/libnettle-6.dll
tesseract_pack/libnghttp2-14.dll
tesseract_pack/libopenjp2.dll
tesseract_pack/libpango-1.0-0.dll
tesseract_pack/libpangocairo-1.0-0.dll
tesseract_pack/libpangoft2-1.0-0.dll
tesseract_pack/libpangowin32-1.0-0.dll
tesseract_pack/libpcre-1.dll
tesseract_pack/libpixman-1-0.dll
tesseract_pack/libpng16-16.dll
tesseract_pack/libssh2-1.dll
tesseract_pack/libstdc++-6.dll
tesseract_pack/libtesseract-5.dll
tesseract_pack/libtiff-5.dll
tesseract_pack/libunistring-2.dll
tesseract_pack/libwebp-7.dll
tesseract_pack/libwinpthread-1.dll
tesseract_pack/libxml2-2.dll
tesseract_pack/libzstd-1.dll
tesseract_pack/lstmeval.1.html
tesseract_pack/lstmeval.exe
tesseract_ocr_data-1.6.dist-info/METADATA
tesseract_ocr_data-1.6.dist-info/WHEEL
tesseract_ocr_data-1.6.dist-info/license
tesseract_ocr_data-1.6.dist-info/top_level.txt
tesseract_ocr_data-1.6.dist-info/RECORD
